{
  "trainingPhrases": [ {
    "parts": [ {
      "text": "I will be back shortly",
      "auto": true
    } ],
    "repeatCount": 1,
    "languageCode": "en"
  }, {
    "parts": [ {
      "text": "I will be back in a bit",
      "auto": true
    } ],
    "repeatCount": 1,
    "languageCode": "en"
  }, {
    "parts": [ {
      "text": "I will be back very shortly",
      "auto": true
    } ],
    "repeatCount": 1,
    "languageCode": "en"
  }, {
    "parts": [ {
      "text": "I will come back",
      "auto": true
    } ],
    "repeatCount": 1,
    "languageCode": "en"
  }, {
    "parts": [ {
      "text": "I promise to come back",
      "auto": true
    } ],
    "repeatCount": 1,
    "languageCode": "en"
  }, {
    "parts": [ {
      "text": "I'll be back",
      "auto": true
    } ],
    "repeatCount": 1,
    "languageCode": "en"
  }, {
    "parts": [ {
      "text": "I'll get back to you in a minute",
      "auto": true
    } ],
    "repeatCount": 1,
    "languageCode": "en"
  }, {
    "parts": [ {
      "text": "be back ",
      "auto": true
    }, {
      "text": "in 5 minutes",
      "parameterId": "date-time",
      "auto": true
    } ],
    "repeatCount": 1,
    "languageCode": "en"
  }, {
    "parts": [ {
      "text": "I'll be back ",
      "auto": true
    }, {
      "text": "in a few minutes",
      "parameterId": "date-time",
      "auto": true
    } ],
    "repeatCount": 1,
    "languageCode": "en"
  } ]
}
